setup.cfg
setup.py
django_todomvc.egg-info/PKG-INFO
django_todomvc.egg-info/SOURCES.txt
django_todomvc.egg-info/dependency_links.txt
django_todomvc.egg-info/not-zip-safe
django_todomvc.egg-info/requires.txt
django_todomvc.egg-info/top_level.txt
tests/dummy_site/__init__.py
tests/dummy_site/settings.py
tests/dummy_site/urls.py
tests/test_views/__init__.py
tests/test_views/test_task_view_set.py
todomvc/__init__.py
todomvc/models.py
todomvc/serializers.py
todomvc/urls.py
todomvc/version.py
todomvc/views.py
todomvc/migrations/0001_initial.py
todomvc/migrations/__init__.py