Metadata-Version: 1.1
Name: django-todomvc
Version: 1.0.0
Summary: TodoMVC django app
Home-page: https://github.com/adonescunha/django-todomvc
Author: Adones Cunha
Author-email: adonescunha@gmail.com
License: UNKNOWN
Download-URL: https://github.com/adonescunha/django-todomvc/archive/v1.0.0.tar.gz
Platform: UNKNOWN
Classifier: Development Status :: 1 - Planning
Classifier: Intended Audience :: Developers
Classifier: License :: OSI Approved :: MIT License
Classifier: Natural Language :: English
Classifier: Operating System :: OS Independent
Classifier: Programming Language :: Python
